btdashboard/__init__.py
btdashboard/app.py
btdashboard/args.py
btdashboard/config.py
btdashboard/dashboard.py
btdashboard/defaults.py
btdashboard/entrypoint.py
btdashboard/extensions.py
btdashboard/lessons.py
btdashboard/logger.py
btdashboard/sidebar.py
btdashboard/static.py
btdashboard/topics.py
btdashboard/websocket.py
btdashboard/webterminal.py
btdashboard/spyder_terminal/__init__.py
btdashboard/spyder_terminal/server/__init__.py
btdashboard/spyder_terminal/server/common.py
btdashboard/spyder_terminal/server/routes.py
btdashboard/spyder_terminal/server/logic/__init__.py
btdashboard/spyder_terminal/server/logic/term_manager.py
btdashboard/spyder_terminal/server/rest/__init__.py
btdashboard/spyder_terminal/server/rest/term_rest.py
btdashboard/spyder_terminal/server/tests/__init__.py
btdashboard/spyder_terminal/server/tests/print_size.py
btdashboard/spyder_terminal/server/tests/test_server.py
btdashboard/spyder_terminal/server/web/__init__.py
btdashboard/spyder_terminal/server/web/main_handler.py
btdashboard/spyder_terminal/server/websockets/__init__.py
btdashboard/spyder_terminal/server/websockets/term_ws.py
btdashboard-1.1.0.data/data/bin/btdashboard.gui/bert.dashboard.e6629510.css
btdashboard-1.1.0.data/data/bin/btdashboard.gui/bert.dashboard.e6629510.css.br
btdashboard-1.1.0.data/data/bin/btdashboard.gui/bert.dashboard.e6629510.css.gz
btdashboard-1.1.0.data/data/bin/btdashboard.gui/bert.dashboard.e6629510.css.map
btdashboard-1.1.0.data/data/bin/btdashboard.gui/index.8457db7f.js
btdashboard-1.1.0.data/data/bin/btdashboard.gui/index.8457db7f.js.br
btdashboard-1.1.0.data/data/bin/btdashboard.gui/index.8457db7f.js.gz
btdashboard-1.1.0.data/data/bin/btdashboard.gui/index.8457db7f.js.map
btdashboard-1.1.0.data/data/bin/btdashboard.gui/index.f4234a38.css
btdashboard-1.1.0.data/data/bin/btdashboard.gui/index.f4234a38.css.br
btdashboard-1.1.0.data/data/bin/btdashboard.gui/index.f4234a38.css.gz
btdashboard-1.1.0.data/data/bin/btdashboard.gui/index.f4234a38.css.map
btdashboard-1.1.0.dist-info/METADATA
btdashboard-1.1.0.dist-info/WHEEL
btdashboard-1.1.0.dist-info/entry_points.txt
btdashboard-1.1.0.dist-info/top_level.txt
btdashboard-1.1.0.dist-info/RECORD
