Metadata-Version: 2.1
Name: btdashboard
Version: 1.1.0
Summary: Bert's Dashboard
Home-page: https://github.com/berttejeda/bert.dashboard
Author: Engelbert Tejeda
Author-email: berttejeda@gmail.com
Keywords: yaml,configuration,config,file,python,settings
Classifier: Development Status :: 3 - Alpha
Classifier: Intended Audience :: Developers
Classifier: Intended Audience :: Information Technology
Classifier: License :: OSI Approved :: MIT License
Classifier: Natural Language :: English
Classifier: Programming Language :: Python :: 3.7
Requires-Python: >=3.7
Requires-Dist: btconfig (<5.0.0,>=4.4.4)
Requires-Dist: coloredlogs (<16.0,>=15.0.0)
Requires-Dist: flask (<3.0,>=2.0.0)
Requires-Dist: flask-cors (==3.0.10)
Requires-Dist: jinja2 (<4.0,>=3.0.0)
Requires-Dist: markdown (<4.0,>=3.3.6)
Requires-Dist: python-dotenv (<1.0,>=0.20.0)
Requires-Dist: pymdown-extensions (<10.0,>=9.0)
Requires-Dist: requests (<3.0.0,>=2.0.0)
Requires-Dist: schema (<1.0.0,>=0.7.5)
Requires-Dist: setuptools
Requires-Dist: tornado (<7.0,>=6.0)
Requires-Dist: terminado (<1.0.0,>=0.12.0)
Requires-Dist: ws4py (<1.0,>=0.5.0)
Requires-Dist: pexpect (<5.0,>=4.8.0) ; sys_platform != "win32"
Requires-Dist: pywinpty (<2.0,>=1.1.3) ; sys_platform == "win32"
Provides-Extra: tests
Requires-Dist: pytest ; extra == 'tests'
Requires-Dist: pytest-cov ; extra == 'tests'
Requires-Dist: coveralls ; extra == 'tests'
Requires-Dist: flake8 ; extra == 'tests'
Requires-Dist: mypy ; extra == 'tests'
